coastseg/UI_models.py
coastseg/__init__.py
coastseg/bbox.py
coastseg/coastseg_logs.py
coastseg/coastseg_map.py
coastseg/common.py
coastseg/exceptions.py
coastseg/map_UI.py
coastseg/roi.py
coastseg/shoreline.py
coastseg/tkinter_window_creator.py
coastseg/transects.py
coastseg/zoo_model.py
coastseg/bounding_boxes/shorelines_bounding_boxes.csv
coastseg/bounding_boxes/transects_bounding_boxes.csv
coastseg/bounding_boxes/usa_shorelines_bounding_boxes.csv
coastseg/bounding_boxes/world_shorelines_bounding_boxes.csv
coastseg/transects/CA_USA_transects.geojson
coastseg/transects/E_aus_transects.geojson
coastseg/transects/Gulf_USA_transects.geojson
coastseg/transects/SE_USA_transects.geojson
coastseg_beta_package-0.1.4.dist-info/LICENSE
coastseg_beta_package-0.1.4.dist-info/METADATA
coastseg_beta_package-0.1.4.dist-info/WHEEL
coastseg_beta_package-0.1.4.dist-info/top_level.txt
coastseg_beta_package-0.1.4.dist-info/RECORD
