Metadata-Version: 2.1
Name: coastseg-beta-package
Version: 0.1.4
Summary: An interactive jupyter notebook for downloading satellite imagery
Author-email: Sharon Fitzpatrick <sharon.fitzpatrick23@gmail.com>
License: MIT License        
Project-URL: Homepage, https://github.com/SatelliteShorelines/CoastSeg
Project-URL: Bug Tracker, https://github.com/SatelliteShorelines/CoastSeg/issues
Classifier: Programming Language :: Python :: 3
Classifier: License :: OSI Approved :: MIT License
Classifier: Operating System :: OS Independent
Requires-Python: >=3.8
License-File: LICENSE
Requires-Dist: coastsat-package (>=0.1.0)
Requires-Dist: area
Requires-Dist: requests
Requires-Dist: doodleverse-utils (>=0.0.11)
Requires-Dist: tqdm
Requires-Dist: leafmap
Requires-Dist: shapely
Requires-Dist: geojson
Requires-Dist: tensorflow
